{
  "$schema": "https://tree-sitter.github.io/tree-sitter/assets/schemas/grammar.schema.json",
  "name": "martian",
  "word": "identifier",
  "rules": {
    "source_file": {
      "type": "SEQ",
      "members": [
        {
          "type": "REPEAT",
          "content": {
            "type": "SYMBOL",
            "name": "include"
          }
        },
        {
          "type": "REPEAT",
          "content": {
            "type": "SYMBOL",
            "name": "_declaration"
          }
        },
        {
          "type": "CHOICE",
          "members": [
            {
              "type": "SYMBOL",
              "name": "call"
            },
            {
              "type": "BLANK"
            }
          ]
        }
      ]
    },
    "include": {
      "type": "SEQ",
      "members": [
        {
          "type": "STRING",
          "value": "@include"
        },
        {
          "type": "FIELD",
          "name": "path",
          "content": {
            "type": "SYMBOL",
            "name": "string"
          }
        }
      ]
    },
    "_declaration": {
      "type": "CHOICE",
      "members": [
        {
          "type": "SYMBOL",
          "name": "filetype_decl"
        },
        {
          "type": "SYMBOL",
          "name": "stage"
        },
        {
          "type": "SYMBOL",
          "name": "pipeline"
        },
        {
          "type": "SYMBOL",
          "name": "struct"
        }
      ]
    },
    "filetype_decl": {
      "type": "SEQ",
      "members": [
        {
          "type": "STRING",
          "value": "filetype"
        },
        {
          "type": "FIELD",
          "name": "name",
          "content": {
            "type": "SYMBOL",
            "name": "dotted_id"
          }
        },
        {
          "type": "STRING",
          "value": ";"
        }
      ]
    },
    "stage": {
      "type": "SEQ",
      "members": [
        {
          "type": "STRING",
          "value": "stage"
        },
        {
          "type": "FIELD",
          "name": "name",
          "content": {
            "type": "SYMBOL",
            "name": "identifier"
          }
        },
        {
          "type": "STRING",
          "value": "("
        },
        {
          "type": "REPEAT",
          "content": {
            "type": "SYMBOL",
            "name": "in_param"
          }
        },
        {
          "type": "REPEAT",
          "content": {
            "type": "SYMBOL",
            "name": "out_param"
          }
        },
        {
          "type": "SYMBOL",
          "name": "src_statement"
        },
        {
          "type": "STRING",
          "value": ")"
        },
        {
          "type": "CHOICE",
          "members": [
            {
              "type": "SYMBOL",
              "name": "split"
            },
            {
              "type": "BLANK"
            }
          ]
        },
        {
          "type": "CHOICE",
          "members": [
            {
              "type": "SYMBOL",
              "name": "using_resources"
            },
            {
              "type": "BLANK"
            }
          ]
        },
        {
          "type": "CHOICE",
          "members": [
            {
              "type": "SYMBOL",
              "name": "retain"
            },
            {
              "type": "BLANK"
            }
          ]
        }
      ]
    },
    "in_param": {
      "type": "SEQ",
      "members": [
        {
          "type": "STRING",
          "value": "in"
        },
        {
          "type": "FIELD",
          "name": "type",
          "content": {
            "type": "SYMBOL",
            "name": "type"
          }
        },
        {
          "type": "FIELD",
          "name": "name",
          "content": {
            "type": "SYMBOL",
            "name": "identifier"
          }
        },
        {
          "type": "CHOICE",
          "members": [
            {
              "type": "FIELD",
              "name": "help",
              "content": {
                "type": "SYMBOL",
                "name": "string"
              }
            },
            {
              "type": "BLANK"
            }
          ]
        },
        {
          "type": "STRING",
          "value": ","
        }
      ]
    },
    "out_param": {
      "type": "SEQ",
      "members": [
        {
          "type": "STRING",
          "value": "out"
        },
        {
          "type": "FIELD",
          "name": "type",
          "content": {
            "type": "SYMBOL",
            "name": "type"
          }
        },
        {
          "type": "CHOICE",
          "members": [
            {
              "type": "FIELD",
              "name": "name",
              "content": {
                "type": "SYMBOL",
                "name": "identifier"
              }
            },
            {
              "type": "BLANK"
            }
          ]
        },
        {
          "type": "CHOICE",
          "members": [
            {
              "type": "SEQ",
              "members": [
                {
                  "type": "FIELD",
                  "name": "help",
                  "content": {
                    "type": "SYMBOL",
                    "name": "string"
                  }
                },
                {
                  "type": "CHOICE",
                  "members": [
                    {
                      "type": "FIELD",
                      "name": "out_name",
                      "content": {
                        "type": "SYMBOL",
                        "name": "string"
                      }
                    },
                    {
                      "type": "BLANK"
                    }
                  ]
                }
              ]
            },
            {
              "type": "BLANK"
            }
          ]
        },
        {
          "type": "STRING",
          "value": ","
        }
      ]
    },
    "src_statement": {
      "type": "SEQ",
      "members": [
        {
          "type": "STRING",
          "value": "src"
        },
        {
          "type": "FIELD",
          "name": "lang",
          "content": {
            "type": "SYMBOL",
            "name": "src_lang"
          }
        },
        {
          "type": "FIELD",
          "name": "cmd",
          "content": {
            "type": "SYMBOL",
            "name": "string"
          }
        },
        {
          "type": "STRING",
          "value": ","
        }
      ]
    },
    "src_lang": {
      "type": "CHOICE",
      "members": [
        {
          "type": "STRING",
          "value": "py"
        },
        {
          "type": "STRING",
          "value": "exec"
        },
        {
          "type": "STRING",
          "value": "comp"
        },
        {
          "type": "STRING",
          "value": "compiled"
        }
      ]
    },
    "split": {
      "type": "SEQ",
      "members": [
        {
          "type": "STRING",
          "value": "split"
        },
        {
          "type": "CHOICE",
          "members": [
            {
              "type": "STRING",
              "value": "using"
            },
            {
              "type": "BLANK"
            }
          ]
        },
        {
          "type": "STRING",
          "value": "("
        },
        {
          "type": "REPEAT",
          "content": {
            "type": "SYMBOL",
            "name": "in_param"
          }
        },
        {
          "type": "REPEAT",
          "content": {
            "type": "SYMBOL",
            "name": "out_param"
          }
        },
        {
          "type": "STRING",
          "value": ")"
        }
      ]
    },
    "using_resources": {
      "type": "SEQ",
      "members": [
        {
          "type": "STRING",
          "value": "using"
        },
        {
          "type": "STRING",
          "value": "("
        },
        {
          "type": "REPEAT",
          "content": {
            "type": "SYMBOL",
            "name": "resource"
          }
        },
        {
          "type": "STRING",
          "value": ")"
        }
      ]
    },
    "resource": {
      "type": "CHOICE",
      "members": [
        {
          "type": "SEQ",
          "members": [
            {
              "type": "FIELD",
              "name": "key",
              "content": {
                "type": "CHOICE",
                "members": [
                  {
                    "type": "STRING",
                    "value": "threads"
                  },
                  {
                    "type": "STRING",
                    "value": "mem_gb"
                  },
                  {
                    "type": "STRING",
                    "value": "memgb"
                  },
                  {
                    "type": "STRING",
                    "value": "vmem_gb"
                  },
                  {
                    "type": "STRING",
                    "value": "vmemgb"
                  }
                ]
              }
            },
            {
              "type": "STRING",
              "value": "="
            },
            {
              "type": "SYMBOL",
              "name": "_number"
            },
            {
              "type": "STRING",
              "value": ","
            }
          ]
        },
        {
          "type": "SEQ",
          "members": [
            {
              "type": "FIELD",
              "name": "key",
              "content": {
                "type": "STRING",
                "value": "special"
              }
            },
            {
              "type": "STRING",
              "value": "="
            },
            {
              "type": "SYMBOL",
              "name": "string"
            },
            {
              "type": "STRING",
              "value": ","
            }
          ]
        },
        {
          "type": "SEQ",
          "members": [
            {
              "type": "FIELD",
              "name": "key",
              "content": {
                "type": "STRING",
                "value": "volatile"
              }
            },
            {
              "type": "STRING",
              "value": "="
            },
            {
              "type": "CHOICE",
              "members": [
                {
                  "type": "STRING",
                  "value": "strict"
                },
                {
                  "type": "STRING",
                  "value": "false"
                }
              ]
            },
            {
              "type": "STRING",
              "value": ","
            }
          ]
        }
      ]
    },
    "retain": {
      "type": "SEQ",
      "members": [
        {
          "type": "STRING",
          "value": "retain"
        },
        {
          "type": "STRING",
          "value": "("
        },
        {
          "type": "REPEAT",
          "content": {
            "type": "SEQ",
            "members": [
              {
                "type": "SYMBOL",
                "name": "ref"
              },
              {
                "type": "STRING",
                "value": ","
              }
            ]
          }
        },
        {
          "type": "STRING",
          "value": ")"
        }
      ]
    },
    "pipeline": {
      "type": "SEQ",
      "members": [
        {
          "type": "STRING",
          "value": "pipeline"
        },
        {
          "type": "FIELD",
          "name": "name",
          "content": {
            "type": "SYMBOL",
            "name": "identifier"
          }
        },
        {
          "type": "STRING",
          "value": "("
        },
        {
          "type": "REPEAT",
          "content": {
            "type": "SYMBOL",
            "name": "in_param"
          }
        },
        {
          "type": "REPEAT",
          "content": {
            "type": "SYMBOL",
            "name": "out_param"
          }
        },
        {
          "type": "STRING",
          "value": ")"
        },
        {
          "type": "STRING",
          "value": "{"
        },
        {
          "type": "REPEAT",
          "content": {
            "type": "SYMBOL",
            "name": "call"
          }
        },
        {
          "type": "SYMBOL",
          "name": "return_statement"
        },
        {
          "type": "CHOICE",
          "members": [
            {
              "type": "SYMBOL",
              "name": "retain"
            },
            {
              "type": "BLANK"
            }
          ]
        },
        {
          "type": "STRING",
          "value": "}"
        }
      ]
    },
    "return_statement": {
      "type": "SEQ",
      "members": [
        {
          "type": "STRING",
          "value": "return"
        },
        {
          "type": "STRING",
          "value": "("
        },
        {
          "type": "REPEAT",
          "content": {
            "type": "SYMBOL",
            "name": "binding"
          }
        },
        {
          "type": "CHOICE",
          "members": [
            {
              "type": "SYMBOL",
              "name": "wildcard_binding"
            },
            {
              "type": "BLANK"
            }
          ]
        },
        {
          "type": "STRING",
          "value": ")"
        }
      ]
    },
    "struct": {
      "type": "SEQ",
      "members": [
        {
          "type": "STRING",
          "value": "struct"
        },
        {
          "type": "FIELD",
          "name": "name",
          "content": {
            "type": "SYMBOL",
            "name": "identifier"
          }
        },
        {
          "type": "STRING",
          "value": "("
        },
        {
          "type": "REPEAT",
          "content": {
            "type": "SYMBOL",
            "name": "struct_field"
          }
        },
        {
          "type": "STRING",
          "value": ")"
        }
      ]
    },
    "struct_field": {
      "type": "SEQ",
      "members": [
        {
          "type": "FIELD",
          "name": "type",
          "content": {
            "type": "SYMBOL",
            "name": "type"
          }
        },
        {
          "type": "FIELD",
          "name": "name",
          "content": {
            "type": "SYMBOL",
            "name": "identifier"
          }
        },
        {
          "type": "CHOICE",
          "members": [
            {
              "type": "SEQ",
              "members": [
                {
                  "type": "FIELD",
                  "name": "help",
                  "content": {
                    "type": "SYMBOL",
                    "name": "string"
                  }
                },
                {
                  "type": "CHOICE",
                  "members": [
                    {
                      "type": "FIELD",
                      "name": "out_name",
                      "content": {
                        "type": "SYMBOL",
                        "name": "string"
                      }
                    },
                    {
                      "type": "BLANK"
                    }
                  ]
                }
              ]
            },
            {
              "type": "BLANK"
            }
          ]
        },
        {
          "type": "STRING",
          "value": ","
        }
      ]
    },
    "call": {
      "type": "SEQ",
      "members": [
        {
          "type": "CHOICE",
          "members": [
            {
              "type": "STRING",
              "value": "map"
            },
            {
              "type": "BLANK"
            }
          ]
        },
        {
          "type": "STRING",
          "value": "call"
        },
        {
          "type": "REPEAT",
          "content": {
            "type": "SYMBOL",
            "name": "modifier"
          }
        },
        {
          "type": "FIELD",
          "name": "callable",
          "content": {
            "type": "SYMBOL",
            "name": "identifier"
          }
        },
        {
          "type": "CHOICE",
          "members": [
            {
              "type": "SEQ",
              "members": [
                {
                  "type": "STRING",
                  "value": "as"
                },
                {
                  "type": "FIELD",
                  "name": "alias",
                  "content": {
                    "type": "SYMBOL",
                    "name": "identifier"
                  }
                }
              ]
            },
            {
              "type": "BLANK"
            }
          ]
        },
        {
          "type": "STRING",
          "value": "("
        },
        {
          "type": "REPEAT",
          "content": {
            "type": "SYMBOL",
            "name": "binding"
          }
        },
        {
          "type": "CHOICE",
          "members": [
            {
              "type": "SYMBOL",
              "name": "wildcard_binding"
            },
            {
              "type": "BLANK"
            }
          ]
        },
        {
          "type": "STRING",
          "value": ")"
        },
        {
          "type": "CHOICE",
          "members": [
            {
              "type": "SYMBOL",
              "name": "call_using"
            },
            {
              "type": "BLANK"
            }
          ]
        }
      ]
    },
    "modifier": {
      "type": "CHOICE",
      "members": [
        {
          "type": "STRING",
          "value": "local"
        },
        {
          "type": "STRING",
          "value": "preflight"
        },
        {
          "type": "STRING",
          "value": "volatile"
        }
      ]
    },
    "call_using": {
      "type": "SEQ",
      "members": [
        {
          "type": "STRING",
          "value": "using"
        },
        {
          "type": "STRING",
          "value": "("
        },
        {
          "type": "REPEAT",
          "content": {
            "type": "SYMBOL",
            "name": "call_modifier"
          }
        },
        {
          "type": "STRING",
          "value": ")"
        }
      ]
    },
    "call_modifier": {
      "type": "CHOICE",
      "members": [
        {
          "type": "SEQ",
          "members": [
            {
              "type": "FIELD",
              "name": "key",
              "content": {
                "type": "CHOICE",
                "members": [
                  {
                    "type": "STRING",
                    "value": "local"
                  },
                  {
                    "type": "STRING",
                    "value": "preflight"
                  },
                  {
                    "type": "STRING",
                    "value": "volatile"
                  }
                ]
              }
            },
            {
              "type": "STRING",
              "value": "="
            },
            {
              "type": "SYMBOL",
              "name": "_bool"
            },
            {
              "type": "STRING",
              "value": ","
            }
          ]
        },
        {
          "type": "SEQ",
          "members": [
            {
              "type": "FIELD",
              "name": "key",
              "content": {
                "type": "STRING",
                "value": "disabled"
              }
            },
            {
              "type": "STRING",
              "value": "="
            },
            {
              "type": "SYMBOL",
              "name": "ref"
            },
            {
              "type": "STRING",
              "value": ","
            }
          ]
        }
      ]
    },
    "binding": {
      "type": "SEQ",
      "members": [
        {
          "type": "FIELD",
          "name": "name",
          "content": {
            "type": "SYMBOL",
            "name": "identifier"
          }
        },
        {
          "type": "STRING",
          "value": "="
        },
        {
          "type": "CHOICE",
          "members": [
            {
              "type": "SYMBOL",
              "name": "_expr"
            },
            {
              "type": "SYMBOL",
              "name": "split_expr"
            }
          ]
        },
        {
          "type": "STRING",
          "value": ","
        }
      ]
    },
    "split_expr": {
      "type": "SEQ",
      "members": [
        {
          "type": "STRING",
          "value": "split"
        },
        {
          "type": "SYMBOL",
          "name": "_expr"
        }
      ]
    },
    "wildcard_binding": {
      "type": "SEQ",
      "members": [
        {
          "type": "STRING",
          "value": "*"
        },
        {
          "type": "STRING",
          "value": "="
        },
        {
          "type": "SYMBOL",
          "name": "ref"
        },
        {
          "type": "STRING",
          "value": ","
        }
      ]
    },
    "_expr": {
      "type": "CHOICE",
      "members": [
        {
          "type": "SYMBOL",
          "name": "float"
        },
        {
          "type": "SYMBOL",
          "name": "integer"
        },
        {
          "type": "SYMBOL",
          "name": "string"
        },
        {
          "type": "SYMBOL",
          "name": "_bool"
        },
        {
          "type": "SYMBOL",
          "name": "null"
        },
        {
          "type": "SYMBOL",
          "name": "array"
        },
        {
          "type": "SYMBOL",
          "name": "map"
        },
        {
          "type": "SYMBOL",
          "name": "ref"
        }
      ]
    },
    "_bool": {
      "type": "CHOICE",
      "members": [
        {
          "type": "SYMBOL",
          "name": "true"
        },
        {
          "type": "SYMBOL",
          "name": "false"
        }
      ]
    },
    "true": {
      "type": "STRING",
      "value": "true"
    },
    "false": {
      "type": "STRING",
      "value": "false"
    },
    "null": {
      "type": "STRING",
      "value": "null"
    },
    "array": {
      "type": "SEQ",
      "members": [
        {
          "type": "STRING",
          "value": "["
        },
        {
          "type": "CHOICE",
          "members": [
            {
              "type": "SEQ",
              "members": [
                {
                  "type": "SEQ",
                  "members": [
                    {
                      "type": "SYMBOL",
                      "name": "_expr"
                    },
                    {
                      "type": "REPEAT",
                      "content": {
                        "type": "SEQ",
                        "members": [
                          {
                            "type": "STRING",
                            "value": ","
                          },
                          {
                            "type": "SYMBOL",
                            "name": "_expr"
                          }
                        ]
                      }
                    }
                  ]
                },
                {
                  "type": "CHOICE",
                  "members": [
                    {
                      "type": "STRING",
                      "value": ","
                    },
                    {
                      "type": "BLANK"
                    }
                  ]
                }
              ]
            },
            {
              "type": "BLANK"
            }
          ]
        },
        {
          "type": "STRING",
          "value": "]"
        }
      ]
    },
    "map": {
      "type": "SEQ",
      "members": [
        {
          "type": "STRING",
          "value": "{"
        },
        {
          "type": "CHOICE",
          "members": [
            {
              "type": "SEQ",
              "members": [
                {
                  "type": "SEQ",
                  "members": [
                    {
                      "type": "SYMBOL",
                      "name": "pair"
                    },
                    {
                      "type": "REPEAT",
                      "content": {
                        "type": "SEQ",
                        "members": [
                          {
                            "type": "STRING",
                            "value": ","
                          },
                          {
                            "type": "SYMBOL",
                            "name": "pair"
                          }
                        ]
                      }
                    }
                  ]
                },
                {
                  "type": "CHOICE",
                  "members": [
                    {
                      "type": "STRING",
                      "value": ","
                    },
                    {
                      "type": "BLANK"
                    }
                  ]
                }
              ]
            },
            {
              "type": "BLANK"
            }
          ]
        },
        {
          "type": "STRING",
          "value": "}"
        }
      ]
    },
    "pair": {
      "type": "SEQ",
      "members": [
        {
          "type": "FIELD",
          "name": "key",
          "content": {
            "type": "CHOICE",
            "members": [
              {
                "type": "SYMBOL",
                "name": "string"
              },
              {
                "type": "SYMBOL",
                "name": "identifier"
              }
            ]
          }
        },
        {
          "type": "STRING",
          "value": ":"
        },
        {
          "type": "FIELD",
          "name": "value",
          "content": {
            "type": "SYMBOL",
            "name": "_expr"
          }
        }
      ]
    },
    "ref": {
      "type": "CHOICE",
      "members": [
        {
          "type": "SYMBOL",
          "name": "self"
        },
        {
          "type": "SEQ",
          "members": [
            {
              "type": "FIELD",
              "name": "base",
              "content": {
                "type": "SYMBOL",
                "name": "identifier"
              }
            },
            {
              "type": "REPEAT",
              "content": {
                "type": "SEQ",
                "members": [
                  {
                    "type": "STRING",
                    "value": "."
                  },
                  {
                    "type": "SYMBOL",
                    "name": "_ref_segment"
                  }
                ]
              }
            }
          ]
        }
      ]
    },
    "self": {
      "type": "SEQ",
      "members": [
        {
          "type": "STRING",
          "value": "self"
        },
        {
          "type": "REPEAT",
          "content": {
            "type": "SEQ",
            "members": [
              {
                "type": "STRING",
                "value": "."
              },
              {
                "type": "SYMBOL",
                "name": "_ref_segment"
              }
            ]
          }
        }
      ]
    },
    "_ref_segment": {
      "type": "CHOICE",
      "members": [
        {
          "type": "SYMBOL",
          "name": "identifier"
        },
        {
          "type": "ALIAS",
          "content": {
            "type": "STRING",
            "value": "default"
          },
          "named": true,
          "value": "identifier"
        }
      ]
    },
    "type": {
      "type": "SEQ",
      "members": [
        {
          "type": "CHOICE",
          "members": [
            {
              "type": "ALIAS",
              "content": {
                "type": "CHOICE",
                "members": [
                  {
                    "type": "STRING",
                    "value": "int"
                  },
                  {
                    "type": "STRING",
                    "value": "float"
                  },
                  {
                    "type": "STRING",
                    "value": "string"
                  },
                  {
                    "type": "STRING",
                    "value": "bool"
                  },
                  {
                    "type": "STRING",
                    "value": "path"
                  }
                ]
              },
              "named": true,
              "value": "primitive_type"
            },
            {
              "type": "SYMBOL",
              "name": "map_type"
            },
            {
              "type": "SYMBOL",
              "name": "dotted_id"
            }
          ]
        },
        {
          "type": "REPEAT",
          "content": {
            "type": "SYMBOL",
            "name": "array_suffix"
          }
        }
      ]
    },
    "map_type": {
      "type": "SEQ",
      "members": [
        {
          "type": "STRING",
          "value": "map"
        },
        {
          "type": "CHOICE",
          "members": [
            {
              "type": "SEQ",
              "members": [
                {
                  "type": "STRING",
                  "value": "<"
                },
                {
                  "type": "SYMBOL",
                  "name": "type"
                },
                {
                  "type": "STRING",
                  "value": ">"
                }
              ]
            },
            {
              "type": "BLANK"
            }
          ]
        }
      ]
    },
    "array_suffix": {
      "type": "SEQ",
      "members": [
        {
          "type": "STRING",
          "value": "["
        },
        {
          "type": "STRING",
          "value": "]"
        }
      ]
    },
    "dotted_id": {
      "type": "SEQ",
      "members": [
        {
          "type": "SYMBOL",
          "name": "identifier"
        },
        {
          "type": "REPEAT",
          "content": {
            "type": "SEQ",
            "members": [
              {
                "type": "STRING",
                "value": "."
              },
              {
                "type": "SYMBOL",
                "name": "identifier"
              }
            ]
          }
        }
      ]
    },
    "identifier": {
      "type": "PATTERN",
      "value": "_?[A-Za-z]\\w*"
    },
    "_number": {
      "type": "CHOICE",
      "members": [
        {
          "type": "SYMBOL",
          "name": "integer"
        },
        {
          "type": "SYMBOL",
          "name": "float"
        }
      ]
    },
    "integer": {
      "type": "PATTERN",
      "value": "-?\\d+"
    },
    "float": {
      "type": "PATTERN",
      "value": "-?\\d+(\\.\\d+([eE][+-]?\\d+)?|[eE][+-]?\\d+)"
    },
    "string": {
      "type": "TOKEN",
      "content": {
        "type": "SEQ",
        "members": [
          {
            "type": "STRING",
            "value": "\""
          },
          {
            "type": "REPEAT",
            "content": {
              "type": "CHOICE",
              "members": [
                {
                  "type": "PATTERN",
                  "value": "[^\"\\\\]"
                },
                {
                  "type": "PATTERN",
                  "value": "\\\\[abfnrtv\\\\\"]"
                },
                {
                  "type": "PATTERN",
                  "value": "\\\\[0-7]{3}"
                },
                {
                  "type": "PATTERN",
                  "value": "\\\\x[0-9a-fA-F]{2}"
                },
                {
                  "type": "PATTERN",
                  "value": "\\\\u[0-9a-fA-F]{4}"
                },
                {
                  "type": "PATTERN",
                  "value": "\\\\U[0-9a-fA-F]{8}"
                }
              ]
            }
          },
          {
            "type": "STRING",
            "value": "\""
          }
        ]
      }
    },
    "comment": {
      "type": "TOKEN",
      "content": {
        "type": "SEQ",
        "members": [
          {
            "type": "STRING",
            "value": "#"
          },
          {
            "type": "PATTERN",
            "value": ".*"
          }
        ]
      }
    }
  },
  "extras": [
    {
      "type": "PATTERN",
      "value": "\\s"
    },
    {
      "type": "SYMBOL",
      "name": "comment"
    }
  ],
  "conflicts": [],
  "precedences": [],
  "externals": [],
  "inline": [],
  "supertypes": [],
  "reserved": {}
}